nutbridge/__init__.py
nutbridge/nutbridge.py
nutbridge-0.0.6.dist-info/METADATA
nutbridge-0.0.6.dist-info/WHEEL
nutbridge-0.0.6.dist-info/entry_points.txt
nutbridge-0.0.6.dist-info/RECORD
