Metadata-Version: 2.1
Name: nutbridge
Version: 0.0.6
Summary: A small wrapper on top of boto3 to make it easier to work with AWS S3
Project-URL: Homepage, https://github.com/squaredev-io/nutbridge
Project-URL: Bug Tracker, https://github.com/squaredev-io/nutbridge/issues
Author-email: Charis Giaralis <charis.giaralis@squaredev.io>
Classifier: License :: OSI Approved :: MIT License
Classifier: Operating System :: OS Independent
Classifier: Programming Language :: Python :: 3
Requires-Python: >=3.7
Requires-Dist: boto3
Requires-Dist: click
Requires-Dist: python-dotenv
Requires-Dist: tqdm
